[
  {
    "name": "Retin-A MICRO",
    "price": 995.98,
    "sellerFullName": "Thomas SNYDER"
  },
  {
    "name": "Smooth texture Orange flavor",
    "price": 976.65,
    "sellerFullName": "Nicole MARTINEZ"
  },
  {
    "name": "Megestrol Acetate",
    "price": 976.15,
    "sellerFullName": "Kathy GILBERT"
  },
  {
    "name": "Dawn Ultra Antibacterial Hand",
    "price": 969.86,
    "sellerFullName": "Anna CLARK"
  },
  {
    "name": "Clearskin",
    "price": 968.59,
    "sellerFullName": "Sarah DAY"
  },
  {
    "name": "NEO-POLY-BAC HYDRO",
    "price": 967.32,
    "sellerFullName": "Rachel JOHNSON"
  },
  {
    "name": "Homeopathic Rheumatism",
    "price": 967.08,
    "sellerFullName": "Clarence FOWLER"
  },
  {
    "name": "Metformin Hydrochloride",
    "price": 953.99,
    "sellerFullName": "Brandon FULLER"
  },
  {
    "name": "Glipizide and Metformin Hydrochloride",
    "price": 953.60,
    "sellerFullName": "Bonnie FOX"
  },
  {
    "name": "pain relief",
    "price": 938.23,
    "sellerFullName": "Patrick KING"
  },
  {
    "name": "Spironolactone",
    "price": 933.69,
    "sellerFullName": "null MITCHELL"
  },
  {
    "name": "Care One Hemorrhoidal",
    "price": 932.18,
    "sellerFullName": "Clarence FOWLER"
  },
  {
    "name": "Ranitidine",
    "price": 926.64,
    "sellerFullName": "Wanda HARRIS"
  },
  {
    "name": "Aspirin",
    "price": 925.45,
    "sellerFullName": "Betty WARD"
  },
  {
    "name": "Myristica Argentum Sinus Relief",
    "price": 904.52,
    "sellerFullName": "Clarence FOWLER"
  },
  {
    "name": "EPZICOM",
    "price": 895.65,
    "sellerFullName": "Carl LAWSON"
  },
  {
    "name": "Levothyroxine Sodium",
    "price": 885.86,
    "sellerFullName": "Carl LAWSON"
  },
  {
    "name": "ESIKA",
    "price": 879.37,
    "sellerFullName": "null SCHMIDT"
  },
  {
    "name": "Perrigo Benzoyl Peroxide",
    "price": 873.24,
    "sellerFullName": "null HARRISON"
  },
  {
    "name": "Shopko Lip Treatment",
    "price": 861.42,
    "sellerFullName": "Diana HARVEY"
  },
  {
    "name": "Moore Medical Sinus Pain and Pressure Relief",
    "price": 855.39,
    "sellerFullName": "null PETERSON"
  },
  {
    "name": "RESCRIPTOR",
    "price": 850.52,
    "sellerFullName": "Fred ALLEN"
  },
  {
    "name": "Aquafresh",
    "price": 849.93,
    "sellerFullName": "Sarah DAY"
  },
  {
    "name": "IOPE SUPER VITAL",
    "price": 824.68,
    "sellerFullName": "Christine GOMEZ"
  },
  {
    "name": "LV-FX",
    "price": 820.87,
    "sellerFullName": "Chris MITCHELL"
  },
  {
    "name": "Azithromycin",
    "price": 813.87,
    "sellerFullName": "Diana HARVEY"
  },
  {
    "name": "Clarins Paris Skin Illusion - 114 cappuccino",
    "price": 811.42,
    "sellerFullName": "Gloria ALEXANDER"
  },
  {
    "name": "Meloxicam",
    "price": 809.18,
    "sellerFullName": "Bonnie FOX"
  },
  {
    "name": "Naproxen",
    "price": 807.22,
    "sellerFullName": "Anna PARKER"
  },
  {
    "name": "Isosorbide Mononitrate",
    "price": 789.91,
    "sellerFullName": "Wanda HARRIS"
  },
  {
    "name": "Pollens - Weeds and Garden Plants, Nettle Urtica dioica",
    "price": 782.77,
    "sellerFullName": "Fred BARNES"
  },
  {
    "name": "Warfarin Sodium",
    "price": 770.05,
    "sellerFullName": "null HARRISON"
  },
  {
    "name": "GOONG SECRET CALMING BATH",
    "price": 742.47,
    "sellerFullName": "null SCHMIDT"
  },
  {
    "name": "Pleo Lat",
    "price": 720.08,
    "sellerFullName": "null MORENO"
  },
  {
    "name": "Prostate",
    "price": 716.05,
    "sellerFullName": "Gloria ALEXANDER"
  },
  {
    "name": "Acnezzol Base",
    "price": 710.60,
    "sellerFullName": "null SCHMIDT"
  },
  {
    "name": "CALMING DIAPER RASH",
    "price": 700.92,
    "sellerFullName": "Wanda HARRIS"
  },
  {
    "name": "CLARINS Ever Matte SPF 15 - 105 Nude",
    "price": 696.06,
    "sellerFullName": "Anna CLARK"
  },
  {
    "name": "PRIMAXIN",
    "price": 686.66,
    "sellerFullName": "Betty LAWSON"
  },
  {
    "name": "Ampicillin",
    "price": 674.63,
    "sellerFullName": "Wanda HARRIS"
  },
  {
    "name": "ENBREL",
    "price": 673.97,
    "sellerFullName": "Jennifer RILEY"
  },
  {
    "name": "Amitiza",
    "price": 666.58,
    "sellerFullName": "Clarence FOWLER"
  },
  {
    "name": "Strattera",
    "price": 658.54,
    "sellerFullName": "Rachel JOHNSON"
  },
  {
    "name": "Childrens Allegra Allergy",
    "price": 650.97,
    "sellerFullName": "Anna CLARK"
  },
  {
    "name": "Imipramine Hydrochloride",
    "price": 648.69,
    "sellerFullName": "null BAKER"
  },
  {
    "name": "AVANDAMET",
    "price": 632.08,
    "sellerFullName": "Brandon FULLER"
  },
  {
    "name": "ziprasidone hydrochloride",
    "price": 628.66,
    "sellerFullName": "Fred BARNES"
  },
  {
    "name": "Foaming Hand Sanitizer",
    "price": 624.72,
    "sellerFullName": "Patricia FULLER"
  },
  {
    "name": "AMARANTHUS PALMERI POLLEN",
    "price": 623.16,
    "sellerFullName": "Gary STEVENS"
  },
  {
    "name": "Glipizide",
    "price": 621.78,
    "sellerFullName": "Betty LAWSON"
  },
  {
    "name": "No7 Protect and Perfect Foundation Sunscreen Broad Spectrum SPF 15 Cool Ivory",
    "price": 616.19,
    "sellerFullName": "null THOMPSON"
  },
  {
    "name": "Diastat",
    "price": 614.14,
    "sellerFullName": "Amanda FRAZIER"
  },
  {
    "name": "Pleo Ginkgo",
    "price": 613.65,
    "sellerFullName": "Gary STEVENS"
  },
  {
    "name": "Ketorolac Tromethamine",
    "price": 608.18,
    "sellerFullName": "Joshua MURRAY"
  },
  {
    "name": "Gemcitabine",
    "price": 594.79,
    "sellerFullName": "Sandra RILEY"
  },
  {
    "name": "Agaricus Equisetum Special Order",
    "price": 585.93,
    "sellerFullName": "Patricia COOPER"
  },
  {
    "name": "AIR",
    "price": 581.69,
    "sellerFullName": "null THOMPSON"
  },
  {
    "name": "Topiramate",
    "price": 578.77,
    "sellerFullName": "Jacqueline PEREZ"
  },
  {
    "name": "Echinacea Quartz Gum Support",
    "price": 570.08,
    "sellerFullName": "Gary STEVENS"
  },
  {
    "name": "PLANTAGO LANCEOLATA POLLEN",
    "price": 561.68,
    "sellerFullName": "Sarah DAY"
  },
  {
    "name": "DAYWEAR PLUS MULTI PROTECTION TINTED MOISTURIZER",
    "price": 555.12,
    "sellerFullName": "Rachel JOHNSON"
  },
  {
    "name": "TERSI",
    "price": 554.91,
    "sellerFullName": "Arthur REYNOLDS"
  },
  {
    "name": "Prednisone",
    "price": 550.72,
    "sellerFullName": "Joshua MURRAY"
  },
  {
    "name": "Propranolol Hydrochloride",
    "price": 546.95,
    "sellerFullName": "Bonnie FOX"
  },
  {
    "name": "Extra Strength Pain Reliever PM",
    "price": 542.72,
    "sellerFullName": "Chris MITCHELL"
  },
  {
    "name": "equaline",
    "price": 520.45,
    "sellerFullName": "null SCHMIDT"
  },
  {
    "name": "Parsley",
    "price": 519.06,
    "sellerFullName": "Jonathan RODRIGUEZ"
  },
  {
    "name": "Allopurinol",
    "price": 518.50,
    "sellerFullName": "null CUNNINGHAM"
  },
  {
    "name": "TRAMADOL HYDROCHLORIDE",
    "price": 516.48,
    "sellerFullName": "Paula HILL"
  }
]